{
  "Data": [
    [
      {
        "PlayerId": "TTV_DONFATHER404#4730568",
        "Kills": 13.0,
        "Assists": 1.0,
        "DamageDone": 4082.0,
        "Executions": 0.0,
        "Score": 8525.0,
        "LongestStreak": 15.0,
        "TeamSurvivalTimeInMilliseconds": 698688.0,
        "TeamPlacement": 4.0,
        "KillScore": 3250,
        "AssistScore": 125,
        "DamageDoneScore": 4082,
        "ExecutionScore": 0,
        "ScoreScore": 2132,
        "LongestStreakScore": 3750,
        "TeamSurvivalTimeInMillisecondsScore": 583,
        "TeamPlacementScore": 1750,
        "TotalScore": 15672
      },
      {
        "PlayerId": "TTV_DONFATHER404#4730568",
        "Kills": 11.0,
        "Assists": 1.0,
        "DamageDone": 3989.0,
        "Executions": 0.0,
        "Score": 8825.0,
        "LongestStreak": 11.0,
        "TeamSurvivalTimeInMilliseconds": 740000.0,
        "TeamPlacement": 1.0,
        "KillScore": 2750,
        "AssistScore": 125,
        "DamageDoneScore": 3989,
        "ExecutionScore": 0,
        "ScoreScore": 2207,
        "LongestStreakScore": 2750,
        "TeamSurvivalTimeInMillisecondsScore": 617,
        "TeamPlacementScore": 2500,
        "TotalScore": 14938
      },
      {
        "PlayerId": "TTV_DONFATHER404#4730568",
        "Kills": 9.0,
        "Assists": 0.0,
        "DamageDone": 3812.0,
        "Executions": 0.0,
        "Score": 4225.0,
        "LongestStreak": 8.0,
        "TeamSurvivalTimeInMilliseconds": 687648.0,
        "TeamPlacement": 3.0,
        "KillScore": 2250,
        "AssistScore": 0,
        "DamageDoneScore": 3812,
        "ExecutionScore": 0,
        "ScoreScore": 1057,
        "LongestStreakScore": 2000,
        "TeamSurvivalTimeInMillisecondsScore": 574,
        "TeamPlacementScore": 2000,
        "TotalScore": 11693
      },
      {
        "PlayerId": "TTV_DONFATHER404#4730568",
        "Kills": 10.0,
        "Assists": 2.0,
        "DamageDone": 4271.0,
        "Executions": 0.0,
        "Score": 3600.0,
        "LongestStreak": 8.0,
        "TeamSurvivalTimeInMilliseconds": 371616.0,
        "TeamPlacement": 6.0,
        "KillScore": 2500,
        "AssistScore": 250,
        "DamageDoneScore": 4271,
        "ExecutionScore": 0,
        "ScoreScore": 900,
        "LongestStreakScore": 2000,
        "TeamSurvivalTimeInMillisecondsScore": 310,
        "TeamPlacementScore": 1250,
        "TotalScore": 11481
      },
      {
        "PlayerId": "TTV_DONFATHER404#4730568",
        "Kills": 9.0,
        "Assists": 0.0,
        "DamageDone": 3545.0,
        "Executions": 0.0,
        "Score": 4550.0,
        "LongestStreak": 10.0,
        "TeamSurvivalTimeInMilliseconds": 433488.0,
        "TeamPlacement": 7.0,
        "KillScore": 2250,
        "AssistScore": 0,
        "DamageDoneScore": 3545,
        "ExecutionScore": 0,
        "ScoreScore": 1138,
        "LongestStreakScore": 2500,
        "TeamSurvivalTimeInMillisecondsScore": 362,
        "TeamPlacementScore": 1000,
        "TotalScore": 10795
      }
    ],
    []
  ]
}